testfiles
rnacounter/rnacounter
rnacounter
