Metadata-Version: 1.1
Name: rnacounter
Version: 1.5.2
Summary: Estimate abundances of genomic features from read densities
Home-page: https://github.com/delafont/rnacounter
Author: Julien Delafontaine
Author-email: julien.delafontaine@epfl.ch
License: GPL-2
Keywords: rna-seq rnaseq count reads table sequencing genetics bioinformatics
Platform: UNKNOWN
Classifier: Programming Language :: Python
Classifier: Programming Language :: Python :: 2.7
Classifier: Programming Language :: Python :: 3
Classifier: Topic :: Scientific/Engineering :: Bio-Informatics
Classifier: Natural Language :: English
Classifier: Operating System :: OS Independent
Classifier: Development Status :: 5 - Production/Stable
